Workbook

Sheet Summary
A1: Customer Profitability & Payment Risk Scorecard
A2: Simulated data (₦) | Reporting date: 30 Sep 2026 | Built with SQL Server and Excel
A4: Key figures
A5: Customers | B5: =COUNTA(Scorecard!A2:A151) -> 150
A6: Net revenue (₦) | B6: =SUM(Scorecard!I2:I151) -> 412124520
A7: Total profit (₦) | B7: =SUM(Scorecard!K2:K151) -> 13362870
A8: Overall profit margin (%) | B8: =IFERROR(B7/B6*100,0) -> 3.2424351
A9: Unprofitable customers | B9: =COUNTIF(Scorecard!K2:K151,"<0") -> 42
A10: Total outstanding (₦) | B10: =SUM(Scorecard!M2:M151) -> 41805530
A11: Total overdue (₦) | B11: =SUM(Scorecard!N2:N151) -> 36184870
A12: High-risk customers | B12: =COUNTIF(Scorecard!V2:V151,"High") -> 17
A13: Net revenue from High-risk customers (₦) | B13: =SUMIFS(Scorecard!I2:I151,Scorecard!V2:V151,"High") -> 68377070
A14: Top 20% customers: share of revenue (%) | B14: =SUM(Scorecard!I2:I31)/SUM(Scorecard!I2:I151)*100 -> 64.478944
A15: Top 20% customers: share of profit (%) | B15: =SUM(Scorecard!K2:K31)/SUM(Scorecard!K2:K151)*100 -> 44.133483
A18: Segment | B18: Low | C18: Medium | D18: High | E18: Total
A19: Corporate | B19: =COUNTIFS(Scorecard!$C$2:$C$151,$A19,Scorecard!$V$2:$V$151,"Low") -> 10 | C19: =COUNTIFS(Scorecard!$C$2:$C$151,$A19,Scorecard!$V$2:$V$151,"Medium") -> 10 | D19: =COUNTIFS(Scorecard!$C$2:$C$151,$A19,Scorecard!$V$2:$V$151,"High") -> 4 | E19: =SUM(B19:D19) -> 24
A20: SME | B20: =COUNTIFS(Scorecard!$C$2:$C$151,$A20,Scorecard!$V$2:$V$151,"Low") -> 25 | C20: =COUNTIFS(Scorecard!$C$2:$C$151,$A20,Scorecard!$V$2:$V$151,"Medium") -> 29 | D20: =COUNTIFS(Scorecard!$C$2:$C$151,$A20,Scorecard!$V$2:$V$151,"High") -> 6 | E20: =SUM(B20:D20) -> 60
A21: Retail | B21: =COUNTIFS(Scorecard!$C$2:$C$151,$A21,Scorecard!$V$2:$V$151,"Low") -> 39 | C21: =COUNTIFS(Scorecard!$C$2:$C$151,$A21,Scorecard!$V$2:$V$151,"Medium") -> 20 | D21: =COUNTIFS(Scorecard!$C$2:$C$151,$A21,Scorecard!$V$2:$V$151,"High") -> 7 | E21: =SUM(B21:D21) -> 66
A23: Top 10 customers by revenue: revenue vs profit
A24: Customer | B24: Net Revenue (₦) | C24: Profit (₦) | D24: Margin (%) | E24: Risk
A25: =Scorecard!B2 -> Obi Ventures Enterprises | B25: =Scorecard!I2 -> 21560410 | C25: =Scorecard!K2 -> 25980 | D25: =Scorecard!L2 -> 0.1 | E25: =Scorecard!V2 -> High
A26: =Scorecard!B3 -> Halima Trading Ltd | B26: =Scorecard!I3 -> 17816040 | C26: =Scorecard!K3 -> -1428080 | D26: =Scorecard!L3 -> -8 | E26: =Scorecard!V3 -> Medium
A27: =Scorecard!B4 -> Bisi Electricals Ltd | B27: =Scorecard!I4 -> 17268180 | C27: =Scorecard!K4 -> -1747100 | D27: =Scorecard!L4 -> -10.1 | E27: =Scorecard!V4 -> Medium
A28: =Scorecard!B5 -> Emeka Energy Enterprises | B28: =Scorecard!I5 -> 16592970 | C28: =Scorecard!K5 -> 2569060 | D28: =Scorecard!L5 -> 15.5 | E28: =Scorecard!V5 -> Low
A29: =Scorecard!B6 -> Obi Logistics Nig Ltd | B29: =Scorecard!I6 -> 15901820 | C29: =Scorecard!K6 -> 4149140 | D29: =Scorecard!L6 -> 26.1 | E29: =Scorecard!V6 -> Low
A30: =Scorecard!B7 -> Ngozi Stores & Sons | B30: =Scorecard!I7 -> 15801870 | C30: =Scorecard!K7 -> -935430 | D30: =Scorecard!L7 -> -5.9 | E30: =Scorecard!V7 -> Medium
A31: =Scorecard!B8 -> Chinedu Fashion Enterprises | B31: =Scorecard!I8 -> 13681740 | C31: =Scorecard!K8 -> 1204790 | D31: =Scorecard!L8 -> 8.8 | E31: =Scorecard!V8 -> Low
A32: =Scorecard!B9 -> Tola Electricals & Sons | B32: =Scorecard!I9 -> 13004420 | C32: =Scorecard!K9 -> 302350 | D32: =Scorecard!L9 -> 2.3 | E32: =Scorecard!V9 -> High
A33: =Scorecard!B10 -> Zainab Fashion & Sons | B33: =Scorecard!I10 -> 11083500 | C33: =Scorecard!K10 -> -125630 | D33: =Scorecard!L10 -> -1.1 | E33: =Scorecard!V10 -> Medium
A34: =Scorecard!B11 -> Funke Agro Enterprises | B34: =Scorecard!I11 -> 10143630 | C34: =Scorecard!K11 -> -565420 | D34: =Scorecard!L11 -> -5.6 | E34: =Scorecard!V11 -> High

Sheet Scorecard
A1: Customer ID | B1: Customer | C1: Segment | D1: City | E1: Credit Terms (days) | F1: Invoices | G1: Gross Revenue (₦) | H1: Discounts (₦) | I1: Net Revenue (₦) | J1: Returns (₦) | K1: Profit (₦) | L1: Profit Margin (%) | M1: Outstanding (₦) | N1: Overdue (₦) | O1: Avg Days Late | P1: Discount (% of gross) | Q1: Overdue (% of net) | R1: Margin Pts | S1: Late Pts | T1: Overdue Pts | U1: Risk Score | V1: Risk Rating
A2: C1015 | B2: Obi Ventures Enterprises | C2: Corporate | D2: Unknown | E2: 45 | F2: 36 | G2: 30775600 | H2: 9215190 | I2: 21560410 | J2: 29180 | K2: 25980 | L2: 0.1 | M2: 6998950 | N2: 5038560 | O2: 39.08 | P2: =IFERROR(H2/G2*100,0) -> 29.943169 | Q2: =IFERROR(N2/I2*100,0) -> 23.3695 | R2: =IF(L2<0,2,IF(L2<Assumptions!$B$4,1,0)) -> 1 | S2: =IF(O2>Assumptions!$B$6,2,IF(O2>Assumptions!$B$5,1,0)) -> 2 | T2: =IF(Q2>Assumptions!$B$8,2,IF(Q2>Assumptions!$B$7,1,0)) -> 2 | U2: =R2+S2+T2 -> 5 | V2: =IF(U2>=Assumptions!$B$10,"High",IF(U2>=Assumptions!$B$9,"Medium","Low")) -> High
A3: C1038 | B3: Halima Trading Ltd | C3: Corporate | D3: Abuja | E3: 45 | F3: 31 | G3: 23317100 | H3: 5501060 | I3: 17816040 | J3: 546320 | K3: -1428080 | L3: -8 | M3: 955520 | N3: 130270 | O3: 12.241379 | P3: =IFERROR(H3/G3*100,0) -> 23.592385 | Q3: =IFERROR(N3/I3*100,0) -> 0.73119504 | R3: =IF(L3<0,2,IF(L3<Assumptions!$B$4,1,0)) -> 2 | S3: =IF(O3>Assumptions!$B$6,2,IF(O3>Assumptions!$B$5,1,0)) -> 0 | T3: =IF(Q3>Assumptions!$B$8,2,IF(Q3>Assumptions!$B$7,1,0)) -> 0 | U3: =R3+S3+T3 -> 2 | V3: =IF(U3>=Assumptions!$B$10,"High",IF(U3>=Assumptions!$B$9,"Medium","Low")) -> Medium
A4: C1064 | B4: Bisi Electricals Ltd | C4: Corporate | D4: Lagos | E4: 45 | F4: 33 | G4: 22601500 | H4: 5333320 | I4: 17268180 | J4: 0 | K4: -1747100 | L4: -10.1 | M4: 1020090 | N4: 0 | O4: 13.366666 | P4: =IFERROR(H4/G4*100,0) -> 23.597195 | Q4: =IFERROR(N4/I4*100,0) -> 0 | R4: =IF(L4<0,2,IF(L4<Assumptions!$B$4,1,0)) -> 2 | S4: =IF(O4>Assumptions!$B$6,2,IF(O4>Assumptions!$B$5,1,0)) -> 0 | T4: =IF(Q4>Assumptions!$B$8,2,IF(Q4>Assumptions!$B$7,1,0)) -> 0 | U4: =R4+S4+T4 -> 2 | V4: =IF(U4>=Assumptions!$B$10,"High",IF(U4>=Assumptions!$B$9,"Medium","Low")) -> Medium
A5: C1100 | B5: Emeka Energy Enterprises | C5: Corporate | D5: Kano | E5: 45 | F5: 21 | G5: 18719300 | H5: 2126330 | I5: 16592970 | J5: 0 | K5: 2569060 | L5: 15.5 | M5: 297220 | N5: 297220 | O5: 20.714285 | P5: =IFERROR(H5/G5*100,0) -> 11.359025 | Q5: =IFERROR(N5/I5*100,0) -> 1.7912405 | R5: =IF(L5<0,2,IF(L5<Assumptions!$B$4,1,0)) -> 0 | S5: =IF(O5>Assumptions!$B$6,2,IF(O5>Assumptions!$B$5,1,0)) -> 1 | T5: =IF(Q5>Assumptions!$B$8,2,IF(Q5>Assumptions!$B$7,1,0)) -> 0 | U5: =R5+S5+T5 -> 1 | V5: =IF(U5>=Assumptions!$B$10,"High",IF(U5>=Assumptions!$B$9,"Medium","Low")) -> Low
A6: C1092 | B6: Obi Logistics Nig Ltd | C6: Corporate | D6: Kano | E6: 30 | F6: 29 | G6: 17048800 | H6: 1146980 | I6: 15901820 | J6: 0 | K6: 4149140 | L6: 26.1 | M6: 2181590 | N6: 2181590 | O6: 4.615384 | P6: =IFERROR(H6/G6*100,0) -> 6.7276289 | Q6: =IFERROR(N6/I6*100,0) -> 13.719121 | R6: =IF(L6<0,2,IF(L6<Assumptions!$B$4,1,0)) -> 0 | S6: =IF(O6>Assumptions!$B$6,2,IF(O6>Assumptions!$B$5,1,0)) -> 0 | T6: =IF(Q6>Assumptions!$B$8,2,IF(Q6>Assumptions!$B$7,1,0)) -> 1 | U6: =R6+S6+T6 -> 1 | V6: =IF(U6>=Assumptions!$B$10,"High",IF(U6>=Assumptions!$B$9,"Medium","Low")) -> Low
A7: C1107 | B7: Ngozi Stores & Sons | C7: Corporate | D7: Kano | E7: 45 | F7: 35 | G7: 20455500 | H7: 4653630 | I7: 15801870 | J7: 438190 | K7: -935430 | L7: -5.9 | M7: 2214740 | N7: 2214740 | O7: 13.16129 | P7: =IFERROR(H7/G7*100,0) -> 22.750018 | Q7: =IFERROR(N7/I7*100,0) -> 14.015683 | R7: =IF(L7<0,2,IF(L7<Assumptions!$B$4,1,0)) -> 2 | S7: =IF(O7>Assumptions!$B$6,2,IF(O7>Assumptions!$B$5,1,0)) -> 0 | T7: =IF(Q7>Assumptions!$B$8,2,IF(Q7>Assumptions!$B$7,1,0)) -> 1 | U7: =R7+S7+T7 -> 3 | V7: =IF(U7>=Assumptions!$B$10,"High",IF(U7>=Assumptions!$B$9,"Medium","Low")) -> Medium
A8: C1077 | B8: Chinedu Fashion Enterprises | C8: Corporate | D8: Kano | E8: 30 | F8: 26 | G8: 17578400 | H8: 3896660 | I8: 13681740 | J8: 762420 | K8: 1204790 | L8: 8.8 | M8: 261460 | N8: 261460 | O8: 11.346153 | P8: =IFERROR(H8/G8*100,0) -> 22.167319 | Q8: =IFERROR(N8/I8*100,0) -> 1.9110142 | R8: =IF(L8<0,2,IF(L8<Assumptions!$B$4,1,0)) -> 0 | S8: =IF(O8>Assumptions!$B$6,2,IF(O8>Assumptions!$B$5,1,0)) -> 0 | T8: =IF(Q8>Assumptions!$B$8,2,IF(Q8>Assumptions!$B$7,1,0)) -> 0 | U8: =R8+S8+T8 -> 0 | V8: =IF(U8>=Assumptions!$B$10,"High",IF(U8>=Assumptions!$B$9,"Medium","Low")) -> Low
A9: C1031 | B9: Tola Electricals & Sons | C9: Corporate | D9: Unknown | E9: 45 | F9: 26 | G9: 16669900 | H9: 3665480 | I9: 13004420 | J9: 360860 | K9: 302350 | L9: 2.3 | M9: 2694310 | N9: 2132330 | O9: 62.545454 | P9: =IFERROR(H9/G9*100,0) -> 21.988614 | Q9: =IFERROR(N9/I9*100,0) -> 16.396963 | R9: =IF(L9<0,2,IF(L9<Assumptions!$B$4,1,0)) -> 1 | S9: =IF(O9>Assumptions!$B$6,2,IF(O9>Assumptions!$B$5,1,0)) -> 2 | T9: =IF(Q9>Assumptions!$B$8,2,IF(Q9>Assumptions!$B$7,1,0)) -> 1 | U9: =R9+S9+T9 -> 4 | V9: =IF(U9>=Assumptions!$B$10,"High",IF(U9>=Assumptions!$B$9,"Medium","Low")) -> High
A10: C1097 | B10: Zainab Fashion & Sons | C10: Corporate | D10: Lagos | E10: 45 | F10: 20 | G10: 13870500 | H10: 2787000 | I10: 11083500 | J10: 1251670 | K10: -125630 | L10: -1.1 | M10: 0 | N10: 0 | O10: 6.2 | P10: =IFERROR(H10/G10*100,0) -> 20.093003 | Q10: =IFERROR(N10/I10*100,0) -> 0 | R10: =IF(L10<0,2,IF(L10<Assumptions!$B$4,1,0)) -> 2 | S10: =IF(O10>Assumptions!$B$6,2,IF(O10>Assumptions!$B$5,1,0)) -> 0 | T10: =IF(Q10>Assumptions!$B$8,2,IF(Q10>Assumptions!$B$7,1,0)) -> 0 | U10: =R10+S10+T10 -> 2 | V10: =IF(U10>=Assumptions!$B$10,"High",IF(U10>=Assumptions!$B$9,"Medium","Low")) -> Medium
A11: C1133 | B11: Funke Agro Enterprises | C11: Corporate | D11: Abuja | E11: 45 | F11: 25 | G11: 14608200 | H11: 4464570 | I11: 10143630 | J11: 421760 | K11: -565420 | L11: -5.6 | M11: 1530220 | N11: 998230 | O11: 61.818181 | P11: =IFERROR(H11/G11*100,0) -> 30.562082 | Q11: =IFERROR(N11/I11*100,0) -> 9.8409544 | R11: =IF(L11<0,2,IF(L11<Assumptions!$B$4,1,0)) -> 2 | S11: =IF(O11>Assumptions!$B$6,2,IF(O11>Assumptions!$B$5,1,0)) -> 2 | T11: =IF(Q11>Assumptions!$B$8,2,IF(Q11>Assumptions!$B$7,1,0)) -> 0 | U11: =R11+S11+T11 -> 4 | V11: =IF(U11>=Assumptions!$B$10,"High",IF(U11>=Assumptions!$B$9,"Medium","Low")) -> High
A12: C1011 | B12: Halima Fashion Ltd | C12: Corporate | D12: Lagos | E12: 45 | F12: 19 | G12: 12445400 | H12: 3781790 | I12: 8663610 | J12: 66410 | K12: 8320 | L12: 0.1 | M12: 226330 | N12: 226330 | O12: 13.722222 | P12: =IFERROR(H12/G12*100,0) -> 30.387051 | Q12: =IFERROR(N12/I12*100,0) -> 2.6124214 | R12: =IF(L12<0,2,IF(L12<Assumptions!$B$4,1,0)) -> 1 | S12: =IF(O12>Assumptions!$B$6,2,IF(O12>Assumptions!$B$5,1,0)) -> 0 | T12: =IF(Q12>Assumptions!$B$8,2,IF(Q12>Assumptions!$B$7,1,0)) -> 0 | U12: =R12+S12+T12 -> 1 | V12: =IF(U12>=Assumptions!$B$10,"High",IF(U12>=Assumptions!$B$9,"Medium","Low")) -> Low
A13: C1089 | B13: Ngozi Pharma & Sons | C13: Corporate | D13: Unknown | E13: 30 | F13: 24 | G13: 13306100 | H13: 4706720 | I13: 8599380 | J13: 760750 | K13: -2771070 | L13: -32.2 | M13: 430140 | N13: 430140 | O13: 10.130434 | P13: =IFERROR(H13/G13*100,0) -> 35.372649 | Q13: =IFERROR(N13/I13*100,0) -> 5.0019885 | R13: =IF(L13<0,2,IF(L13<Assumptions!$B$4,1,0)) -> 2 | S13: =IF(O13>Assumptions!$B$6,2,IF(O13>Assumptions!$B$5,1,0)) -> 0 | T13: =IF(Q13>Assumptions!$B$8,2,IF(Q13>Assumptions!$B$7,1,0)) -> 0 | U13: =R13+S13+T13 -> 2 | V13: =IF(U13>=Assumptions!$B$10,"High",IF(U13>=Assumptions!$B$9,"Medium","Low")) -> Medium
... A151: C1042 | B151: Ngozi Supplies Nig Ltd | C151: Retail | D151: Lagos | E151: 0 | F151: 2 | G151: 64500 | H151: 4290 | I151: 60210 | J151: 0 | K151: 13140 | L151: 21.8 | M151: 0 | N151: 0 | O151: 9 | P151: =IFERROR(H151/G151*100,0) -> 6.6511628 | Q151: =IFERROR(N151/I151*100,0) -> 0 | R151: =IF(L151<0,2,IF(L151<Assumptions!$B$4,1,0)) -> 0 | S151: =IF(O151>Assumptions!$B$6,2,IF(O151>Assumptions!$B$5,1,0)) -> 0 | T151: =IF(Q151>Assumptions!$B$8,2,IF(Q151>Assumptions!$B$7,1,0)) -> 0 | U151: =R151+S151+T151 -> 0 | V151: =IF(U151>=Assumptions!$B$10,"High",IF(U151>=Assumptions!$B$9,"Medium","Low")) -> Low

Sheet Assumptions
A1: Assumptions & Notes
A2: Edit the blue cells to change how risk is rated. Everything else recalculates.
A3: Setting | B3: Value | C3: What it means
A4: Margin warning threshold (%) | B4: 5 | C4: Profit margin below this earns 1 risk point; below 0% earns 2
A5: Avg days late: medium | B5: 15 | C5: Average days paid after due date above this earns 1 point
A6: Avg days late: high | B6: 30 | C6: Above this earns 2 points
A7: Overdue % of revenue: medium | B7: 10 | C7: Overdue amount as % of net revenue above this earns 1 point
A8: Overdue % of revenue: high | B8: 20 | C8: Above this earns 2 points
A9: Risk score for MEDIUM | B9: 2 | C9: Total points at or above this = Medium
A10: Risk score for HIGH | B10: 4 | C10: Total points at or above this = High
A13: Data: SIMULATED customer finance data (naira) created for a portfolio project. Not a real company.
A14: Source: customer_summary table built in SQL Server from invoices, payments and returns.
A15: Profit = gross amount - discount - returns - cost of goods - delivery cost.
A16: Overdue and aging use 30 Sep 2026 as the reporting date.
A17: Scorecard rows are sorted by net revenue (highest first); the top-20% figure on Summary relies on this.
